{
 "date": "20260714",
 "updated": "09:12:19",
 "races": [
  {
   "race_id": "202607142102",
   "jcd": "21",
   "rno": 2,
   "deadline": "08:58",
   "exhibition": {
    "1": 6.86,
    "2": 6.85,
    "3": 6.9,
    "4": 6.88,
    "5": 6.89,
    "6": 6.88
   },
   "win_prob": {
    "1": 0.4281,
    "2": 0.2317,
    "3": 0.0769,
    "4": 0.2181,
    "5": 0.0122,
    "6": 0.033
   },
   "top10": [
    {
     "combo": "1-2-4",
     "prob": 0.04964
    },
    {
     "combo": "1-4-6",
     "prob": 0.04846
    },
    {
     "combo": "1-4-3",
     "prob": 0.03951
    },
    {
     "combo": "2-1-4",
     "prob": 0.03937
    },
    {
     "combo": "1-4-2",
     "prob": 0.03806
    },
    {
     "combo": "1-2-6",
     "prob": 0.03087
    },
    {
     "combo": "4-1-6",
     "prob": 0.03076
    },
    {
     "combo": "1-4-5",
     "prob": 0.02988
    },
    {
     "combo": "1-3-4",
     "prob": 0.0287
    },
    {
     "combo": "1-2-3",
     "prob": 0.02517
    }
   ],
   "morning_win_prob": {
    "1": 0.6005,
    "2": 0.0874,
    "3": 0.0591,
    "4": 0.2213,
    "5": 0.0125,
    "6": 0.0192
   },
   "delta_comment": "1号艇が展示2位で評価低下(朝60.1%→直前42.8%)"
  },
  {
   "race_id": "202607142302",
   "jcd": "23",
   "rno": 2,
   "deadline": "09:10",
   "exhibition": {
    "1": 6.69,
    "2": 6.7,
    "3": 6.8,
    "4": 6.73,
    "5": 6.68,
    "6": 6.73
   },
   "win_prob": {
    "1": 0.6161,
    "2": 0.2995,
    "3": 0.0277,
    "4": 0.0482,
    "5": 0.0,
    "6": 0.0086
   },
   "top10": [
    {
     "combo": "1-3-2",
     "prob": 0.12754
    },
    {
     "combo": "2-1-3",
     "prob": 0.08095
    },
    {
     "combo": "1-3-4",
     "prob": 0.07205
    },
    {
     "combo": "1-4-2",
     "prob": 0.06903
    },
    {
     "combo": "1-2-3",
     "prob": 0.06736
    },
    {
     "combo": "2-1-4",
     "prob": 0.06647
    },
    {
     "combo": "1-2-4",
     "prob": 0.05531
    },
    {
     "combo": "1-3-6",
     "prob": 0.05001
    },
    {
     "combo": "1-4-3",
     "prob": 0.04749
    },
    {
     "combo": "2-1-6",
     "prob": 0.04614
    }
   ],
   "morning_win_prob": {
    "1": 0.7482,
    "2": 0.1027,
    "3": 0.0813,
    "4": 0.0586,
    "5": 0.0016,
    "6": 0.0077
   },
   "delta_comment": "2号艇が展示3位で評価上昇(朝10.3%→直前29.9%)"
  },
  {
   "race_id": "202607142103",
   "jcd": "21",
   "rno": 3,
   "deadline": "09:24",
   "exhibition": {
    "1": 6.87,
    "2": 6.87,
    "3": 6.84,
    "4": 6.84,
    "5": 6.81,
    "6": 6.77
   },
   "win_prob": {
    "1": 0.1614,
    "2": 0.0355,
    "3": 0.3168,
    "4": 0.1052,
    "5": 0.3467,
    "6": 0.0344
   },
   "top10": [
    {
     "combo": "3-1-5",
     "prob": 0.07184
    },
    {
     "combo": "5-1-3",
     "prob": 0.05757
    },
    {
     "combo": "3-4-5",
     "prob": 0.03966
    },
    {
     "combo": "1-3-5",
     "prob": 0.03581
    },
    {
     "combo": "5-3-1",
     "prob": 0.03221
    },
    {
     "combo": "5-4-3",
     "prob": 0.03181
    },
    {
     "combo": "3-1-2",
     "prob": 0.02997
    },
    {
     "combo": "5-3-2",
     "prob": 0.02975
    },
    {
     "combo": "3-1-4",
     "prob": 0.0288
    },
    {
     "combo": "5-3-4",
     "prob": 0.02859
    }
   ],
   "morning_win_prob": {
    "1": 0.4264,
    "2": 0.0294,
    "3": 0.3597,
    "4": 0.072,
    "5": 0.0941,
    "6": 0.0184
   },
   "delta_comment": "1号艇が展示5位で評価低下(朝42.6%→直前16.1%)"
  }
 ]
}